spotifycl/__init__.py
spotifycl/cli.py
spotifycl/search.py
spotifycl/set_credentials.py
spotifycl/set_env.py
spotifycl/spotify_play.py
spotifycl/spotify_queue.py
spotifycl/spotify_status.py
spotifyCL-1.3.3.dist-info/LICENSE
spotifyCL-1.3.3.dist-info/METADATA
spotifyCL-1.3.3.dist-info/WHEEL
spotifyCL-1.3.3.dist-info/entry_points.txt
spotifyCL-1.3.3.dist-info/top_level.txt
spotifyCL-1.3.3.dist-info/RECORD
