Metadata-Version: 2.1
Name: spotifyCL
Version: 1.3.3
Summary: A command line interface for Spotify
Home-page: https://github.com/Huckdirks/spotifyCL
Author: Huck Dirksmeier
Author-email: Huckdirks@gmail.com
Keywords: Spotify,API,Spotify API,Web API
Classifier: Programming Language :: Python
Classifier: License :: OSI Approved :: MIT License
Classifier: Operating System :: OS Independent
Requires-Python: >=3.8
License-File: LICENSE
Requires-Dist: python-dotenv
Requires-Dist: spotipy
Requires-Dist: rich
